{
  "$schema": "http://json-schema.org/draft-07/schema#",
  "title": "Sonic Screwdriver Device",
  "description": "Schema version 1.1",
  "type": "object",
  "additionalProperties": false,
  "required": [
    "id",
    "vendor",
    "model",
    "year",
    "bios",
    "secure_boot",
    "tpm",
    "usb_boot",
    "uefi_native",
    "reflash_potential",
    "methods",
    "last_seen",
    "windows10_boot",
    "media_mode",
    "udos_launcher"
  ],
  "properties": {
    "id": { "type": "string" },
    "vendor": { "type": "string" },
    "model": { "type": "string" },
    "variant": { "type": "string" },
    "year": { "type": "integer" },
    "cpu": { "type": "string" },
    "gpu": { "type": "string" },
    "ram_gb": { "type": "integer" },
    "storage_gb": { "type": "integer" },
    "bios": { "type": "string", "enum": ["UEFI", "Legacy", "UEFI+Legacy", "unknown"] },
    "secure_boot": { "type": "string", "enum": ["yes", "no", "unknown"] },
    "tpm": { "type": "string", "enum": ["yes", "no", "unknown"] },
    "usb_boot": { "type": "string", "enum": ["native", "uefi_only", "legacy_only", "mixed", "none"] },
    "uefi_native": { "type": "string", "enum": ["works", "issues", "unknown"] },
    "reflash_potential": { "type": "string", "enum": ["high", "medium", "low", "unknown"] },
    "methods": {
      "type": "array",
      "items": { "type": "string" }
    },
    "notes": { "type": "string" },
    "sources": {
      "type": "array",
      "items": { "type": "string" }
    },
    "last_seen": { "type": "string", "format": "date" },
    "windows10_boot": { "type": "string", "enum": ["none", "install", "wtg", "unknown"] },
    "media_mode": { "type": "string", "enum": ["none", "htpc", "retro", "unknown"] },
    "udos_launcher": { "type": "string", "enum": ["none", "basic", "advanced", "unknown"] },
    "wizard_profile": { "type": "string" },
    "media_launcher": { "type": "string" }
  }
}
